hydiomatic/__init__.py
hydiomatic/core.hy
hydiomatic/macros.hy
hydiomatic/rules.hy
hydiomatic/scripts.hy
hydiomatic/utils.hy
hydiomatic/rulesets/__init__.py
hydiomatic/rulesets/arithmetico.hy
hydiomatic/rulesets/collectiono.hy
hydiomatic/rulesets/control_structo.hy
hydiomatic/rulesets/equalityo.hy
hydiomatic/rulesets/grand_cleanupo.hy
hydiomatic/rulesets/jokeo.hy
hydiomatic/rulesets/optimo.hy
hydiomatic/rulesets/quoteo.hy
hydiomatic/rulesets/syntaxo.hy
hydiomatic/rulesets/test.hy
hydiomatic/rulesets/warningso.hy
hydiomatic-0.2.0.dist-info/METADATA
hydiomatic-0.2.0.dist-info/WHEEL
hydiomatic-0.2.0.dist-info/entry_points.txt
hydiomatic-0.2.0.dist-info/top_level.txt
hydiomatic-0.2.0.dist-info/RECORD
