Metadata-Version: 2.1
Name: hydiomatic
Version: 0.2.0
Summary: UNKNOWN
Home-page: https://github.com/hylang/hydiomatic
Author: Gergely Nagy
Author-email: algernon@madhouse-project.org
License: LGPL-3
Platform: any
Classifier: Development Status :: 3 - Alpha
Classifier: Intended Audience :: Developers
Classifier: License :: DFSG approved
Classifier: License :: OSI Approved :: GNU Lesser General Public License v3 or later (LGPLv3+)
Classifier: Operating System :: OS Independent
Classifier: Programming Language :: Lisp
Classifier: Topic :: Software Development :: Libraries
Requires-Python: >=3.4
Requires-Dist: hy (>=0.15)
Requires-Dist: adderall (>=2.0.0)
